{
	"info": {
		"_postman_id": "f3d9d136-037b-4c8c-9f81-1494835480ab",
		"name": "Student",
		"schema": "https://schema.getpostman.com/json/collection/v2.1.0/collection.json",
		"_exporter_id": "31652111"
	},
	"item": [
		{
			"name": "CreateStudent",
			"request": {
				"method": "POST",
				"header": [],
				"body": {
					"mode": "raw",
					"raw": "{\"Name\": \"Zed Sharma\", \"Enroll\": \"202V202\", \"Place\": \"Raogarh\", \"In\": \"8:55 AM\", \"Out\": \"4:55 PM\"}\r\n",
					"options": {
						"raw": {
							"language": "json"
						}
					}
				},
				"url": {
					"raw": "http://localhost:3000/student",
					"protocol": "http",
					"host": [
						"localhost"
					],
					"port": "3000",
					"path": [
						"student"
					]
				}
			},
			"response": []
		},
		{
			"name": "IndexStudents",
			"request": {
				"method": "GET",
				"header": []
			},
			"response": []
		},
		{
			"name": "ShowStudent",
			"request": {
				"method": "GET",
				"header": []
			},
			"response": []
		},
		{
			"name": "UpdateStudent",
			"request": {
				"method": "PUT",
				"header": [],
				"body": {
					"mode": "raw",
					"raw": "{\r\n    \r\n    \"In\":\"8:30 AM\"\r\n}",
					"options": {
						"raw": {
							"language": "json"
						}
					}
				},
				"url": {
					"raw": "http://localhost:3000/student/10",
					"protocol": "http",
					"host": [
						"localhost"
					],
					"port": "3000",
					"path": [
						"student",
						"10"
					]
				}
			},
			"response": []
		},
		{
			"name": "DeleteStudent",
			"request": {
				"method": "DELETE",
				"header": [],
				"url": {
					"raw": "http://localhost:3000/student/9",
					"protocol": "http",
					"host": [
						"localhost"
					],
					"port": "3000",
					"path": [
						"student",
						"9"
					]
				}
			},
			"response": []
		}
	]
}